spip2md/__main__.py
spip2md/config.py
spip2md/extended_models.py
spip2md/lib.py
spip2md/regexmaps.py
spip2md/spip_models.py
spip2md/style.py
spip2md-0.1.1.dist-info/COPYING
spip2md-0.1.1.dist-info/LICENSE
spip2md-0.1.1.dist-info/METADATA
spip2md-0.1.1.dist-info/WHEEL
spip2md-0.1.1.dist-info/entry_points.txt
spip2md-0.1.1.dist-info/RECORD
