Metadata-Version: 2.1
Name: spip2md
Version: 0.1.1
Summary: Generate a static website with plain Markdown+YAML files from a SPIP CMS database
Home-page: https://git.irsamc.ups-tlse.fr/LCPQ/spip2md
License: GPL-2.0
Keywords: Markdown,Static website,SPIP,Converter,Exporter
Author: Guilhem Fauré
Author-email: guilhem.faure@gfaure.eu
Requires-Python: >=3.9,<4.0
Classifier: Development Status :: 3 - Alpha
Classifier: Environment :: Console
Classifier: License :: OSI Approved :: GNU General Public License v2 (GPLv2)
Classifier: License :: OSI Approved :: GNU General Public License v2 or later (GPLv2+)
Classifier: Operating System :: POSIX :: Linux
Classifier: Programming Language :: Python :: 3
Classifier: Programming Language :: Python :: 3.9
Classifier: Programming Language :: Python :: 3.10
Classifier: Programming Language :: Python :: 3.11
Classifier: Topic :: Text Processing
Requires-Dist: peewee (>=3.16.2,<4.0.0)
Requires-Dist: pymysql (>=1.0.3,<2.0.0)
Requires-Dist: python-slugify[unidecode] (>=8.0.1,<9.0.0)
Requires-Dist: pyyaml (>=6.0,<7.0)
Project-URL: Repository, https://git.irsamc.ups-tlse.fr/LCPQ/spip2md
